octopus_ml/__init__.py
octopus_ml/misc.py
octopus_ml/octopus_data.py
octopus_ml/octopus_ml.py
octopus_ml-3.2.0.dist-info/LICENSE
octopus_ml-3.2.0.dist-info/METADATA
octopus_ml-3.2.0.dist-info/WHEEL
octopus_ml-3.2.0.dist-info/top_level.txt
octopus_ml-3.2.0.dist-info/RECORD
