Metadata-Version: 2.1
Name: octopus-ml
Version: 3.2.0
Summary: A collection of handy ML and data validation tools
Home-page: https://github.com/gershonc/octopus-ml
Author: Gershon Celniker
Author-email: gershonc@gmail.com
License: MIT
Classifier: License :: OSI Approved :: MIT License
Classifier: Programming Language :: Python :: 3 :: Only
Classifier: Topic :: Scientific/Engineering
Classifier: Development Status :: 4 - Beta
License-File: LICENSE
Requires-Dist: numpy
Requires-Dist: pandas
Requires-Dist: tqdm
Requires-Dist: lightgbm
Requires-Dist: seaborn
